LICENSE
MANIFEST.in
README.rst
setup.cfg
setup.py
jambi/__init__.py
jambi/config.py
jambi/exceptions.py
jambi/jambi.py
jambi/migration_template.py
jambi/version.py
jambi.egg-info/PKG-INFO
jambi.egg-info/SOURCES.txt
jambi.egg-info/dependency_links.txt
jambi.egg-info/entry_points.txt
jambi.egg-info/not-zip-safe
jambi.egg-info/requires.txt
jambi.egg-info/top_level.txt